<?xml version='1.0' encoding='UTF-8'?>
<catalog xmlns="http://www.intertrust.ru/schema/palette/cat-ui">
  <custom-descriptor ident="Processes" view="(vw_cmj_wf_process)" id="Processes-instances" name="Процессы - экземпляры" style="default">
    <builder name="ru.intertrust.cmj.af.collections.impl.BuilderDominoView">
      <config>
        <view-complex-classif level-select="last"/>
      </config>
    </builder>
    <table>
      <columns>
        <column-ref ref="self"/>
        <column-ref ref="name" sort-asc="true" category="true"/>
        <column-ref ref="created"/>
        <column-ref ref="modified"/>
        <column-ref ref="status"/>
      </columns>
    </table>
  </custom-descriptor>
</catalog>