<?xml version='1.0' encoding='UTF-8'?>
<catalog xmlns="http://www.intertrust.ru/schema/palette/cat-ui">
  <custom-descriptor ident="CardsInputDocs" view="(vw_cmj_13)" id="dp-13-cardsinput" name="Картотека ВхД - для установки связей" style="default">
    <builder name="ru.intertrust.cmj.af.collections.impl.BuilderDominoView"/>
    <table>
      <columns>
        <column-ref ref="docNumber"/>
        <column-ref ref="docDate"/>
        <column-ref ref="regNumber" sort-desc="true"/>
        <column-ref ref="correspondentOrganization"/>
        <column-ref ref="subject"/>
        <column-ref ref="self"/>
      </columns>
    </table>
  </custom-descriptor>
</catalog>