<?xml version='1.0' encoding='UTF-8'?>
<catalog xmlns="http://www.intertrust.ru/schema/palette/cat-ui">
  <descriptor id-sql="dummy" fulltext="true" id="sodlg-org-subjects-h" name="Иерархия" style="default">
    <builder name="ru.intertrust.cmj.af.so.impl.BuilderSODlg"/>
    <table>
      <hierarchy-column descriptor-ref="sodlg-org-subjects-h" column-ref="empty"/>
      <columns>
        <column-ref ref="self"/>
        <column-ref ref="empty"/>
        <column-ref ref="soDlgMixName"/>
        <column-ref ref="soCode"/>
        <column-ref ref="soPost"/>
      </columns>
    </table>
    <dialog-actions>
      <action-ref ref="SO-CreateNonSysPersonDlg"/>
    </dialog-actions>
    <actions>
      <action id="SO-CreateNonSysPersonDlg" name="${catalog.descriptor.sodlg-org-subjects-h.actions.action.SO-CreateNonSysPersonDlg.name:Добавить работника}">
        <create object-ref="NONSYS_HUMAN"/>
      </action>
    </actions>
  </descriptor>
</catalog>